{
  "status": "updated",
  "fqn": "StateStoreSecrets",
  "logicalId": "StateStoreSecrets",
  "instanceId": "d55f8af060531e3b10006a86848b0b4b",
  "resourceType": "Cloudflare.SecretsStore",
  "attr": {
    "storeId": "206d23ae34f74dcca4530f253b4c5b9e",
    "storeName": "default_secrets_store",
    "accountId": "3a855f7ef3ac127682a419eddeb9f884"
  },
  "bindings": [],
  "providerVersion": 0,
  "downstream": [
    "AlchemyStateStoreToken",
    "StateStoreEncryptionKey"
  ],
  "removalPolicy": "destroy"
}